LICENSE
README.md
pyproject.toml
setup.py
rgbxyzlab/__init__.py
rgbxyzlab/primaries.py
rgbxyzlab.egg-info/PKG-INFO
rgbxyzlab.egg-info/SOURCES.txt
rgbxyzlab.egg-info/dependency_links.txt
rgbxyzlab.egg-info/top_level.txt
src/hex.c
src/hls.c
src/hsv.c
src/lab.c
src/luminance.c
src/luv.c
src/rgb.c
src/rgbxyzlabmodule.c
src/xyz.c
tests/test_hex_to_lab.py
tests/test_hex_to_rgb.py
tests/test_hex_to_xyz.py
tests/test_hls_to_rgb.py
tests/test_hsv_to_rgb.py
tests/test_lab_to_rgb.py
tests/test_lab_to_xyz.py
tests/test_luv_to_rgb.py
tests/test_rgb_to_hex.py
tests/test_rgb_to_hls.py
tests/test_rgb_to_hsv.py
tests/test_rgb_to_lab.py
tests/test_rgb_to_xyz.py
tests/test_xyz_to_lab.py