Metadata-Version: 2.4
Name: rgbxyzlab
Version: 0.9.0
Summary: Color space conversion module
Author-email: Morten Kjeldgaard <mok0@mailbox.org>
License-Expression: EUPL-1.2
Project-URL: Codeberg, http://codeberg.org/mok0/rgbxyzlab
Project-URL: Bug reports, https://codeberg.org/mok0/rgbxyzlab/issues
Classifier: Programming Language :: Python :: 3
Classifier: Programming Language :: C
Classifier: Intended Audience :: Education
Classifier: Topic :: Software Development :: Libraries :: Python Modules
Classifier: Topic :: Multimedia :: Graphics :: Graphics Conversion
Classifier: Topic :: Multimedia :: Graphics
Requires-Python: >=3.10
License-File: LICENSE
Dynamic: license-file
